one_id/__init__.py
one_id/core.py
one_id/exceptions.py
one_id/schemas.py
oneid_client-0.1.5.dist-info/METADATA
oneid_client-0.1.5.dist-info/WHEEL
oneid_client-0.1.5.dist-info/top_level.txt
oneid_client-0.1.5.dist-info/RECORD
