Metadata-Version: 2.4
Name: oneid-client
Version: 0.1.5
Summary: A client for OneID authentication
Author-email: Abror Izzatullayev <izzatullev2001abror@gmail.com>
License: MIT
Project-URL: Homepage, https://github.com/justbackend/oneid-client
Requires-Python: >=3.7
Requires-Dist: requests
